formatter/__init__.py
formatter/formatter.py
custom_formatter-0.1.0.dist-info/LICENSE
custom_formatter-0.1.0.dist-info/METADATA
custom_formatter-0.1.0.dist-info/WHEEL
custom_formatter-0.1.0.dist-info/top_level.txt
custom_formatter-0.1.0.dist-info/RECORD
